zyeco/HelloWorld.py
zyeco/__init__.py
zy_predict_tool-0.0.6.dist-info/LICENSE.txt
zy_predict_tool-0.0.6.dist-info/METADATA
zy_predict_tool-0.0.6.dist-info/WHEEL
zy_predict_tool-0.0.6.dist-info/top_level.txt
zy_predict_tool-0.0.6.dist-info/zip-safe
zy_predict_tool-0.0.6.dist-info/RECORD
